hajkr_facebook_scraper/__main__.py
hajkr_facebook_scraper-0.2.2.dist-info/entry_points.txt
hajkr_facebook_scraper-0.2.2.dist-info/WHEEL
hajkr_facebook_scraper-0.2.2.dist-info/METADATA
hajkr_facebook_scraper-0.2.2.dist-info/RECORD
