Metadata-Version: 2.1
Name: hajkr-facebook-scraper
Version: 0.2.2
Summary: 
Author: Tadej Hribar
Requires-Python: >=3.6,<4.0
Classifier: Programming Language :: Python :: 3
Classifier: Programming Language :: Python :: 3.10
Classifier: Programming Language :: Python :: 3.6
Classifier: Programming Language :: Python :: 3.7
Classifier: Programming Language :: Python :: 3.8
Classifier: Programming Language :: Python :: 3.9
Requires-Dist: facebook-scraper (>=0.2,<0.3)
